onthefly/__init__.py
onthefly/cli.py
onthefly/onthefly.py
onthefly-1.1.7.dist-info/AUTHORS.rst
onthefly-1.1.7.dist-info/LICENSE
onthefly-1.1.7.dist-info/METADATA
onthefly-1.1.7.dist-info/WHEEL
onthefly-1.1.7.dist-info/entry_points.txt
onthefly-1.1.7.dist-info/top_level.txt
onthefly-1.1.7.dist-info/RECORD
