Metadata-Version: 2.1
Name: onthefly
Version: 1.1.7
Summary: Type like a god on-the-fly
Home-page: https://github.com/mroavi/onthefly
Author: Martin Roa Villescas
License: MIT license
Keywords: onthefly
Classifier: Development Status :: 2 - Pre-Alpha
Classifier: Intended Audience :: Developers
Classifier: License :: OSI Approved :: MIT License
Classifier: Natural Language :: English
Classifier: Programming Language :: Python :: 3
Classifier: Programming Language :: Python :: 3.5
Classifier: Programming Language :: Python :: 3.6
Classifier: Programming Language :: Python :: 3.7
Classifier: Programming Language :: Python :: 3.8
Classifier: Programming Language :: Python :: 3.9
Classifier: Programming Language :: Python :: 3.10
Requires-Python: >=3.5
License-File: LICENSE
License-File: AUTHORS.rst
Requires-Dist: Click (>=7.0)
Requires-Dist: evdev
Requires-Dist: appdirs
Requires-Dist: elevate
